rxngraphormer/__init__.py
rxngraphormer/data.py
rxngraphormer/eval.py
rxngraphormer/ext_feat.py
rxngraphormer/layer.py
rxngraphormer/model.py
rxngraphormer/rxn_emb.py
rxngraphormer/scheduler.py
rxngraphormer/train.py
rxngraphormer/utils.py
rxngraphormer/midgen/MechFinder.py
rxngraphormer/midgen/__init__.py
rxngraphormer/midgen/midmol.py
rxngraphormer/midgen/LocalTemplate/__init__.py
rxngraphormer/midgen/LocalTemplate/template_extract_extention.py
rxngraphormer/midgen/LocalTemplate/template_extract_utils.py
rxngraphormer/midgen/LocalTemplate/template_extractor.py
rxngraphormer/midgen/collections/LRT_library.csv
rxngraphormer/midgen/collections/MT_library.csv
rxngraphormer/midgen/collections/__init__.py
rxngraphormer/midgen/utils/__init__.py
rxngraphormer/midgen/utils/arrow_pushing.py
rxngraphormer/midgen/utils/criterions.py
rxngraphormer/midgen/utils/utils.py
rxngraphormer-1.0.1.dist-info/LICENSE
rxngraphormer-1.0.1.dist-info/METADATA
rxngraphormer-1.0.1.dist-info/WHEEL
rxngraphormer-1.0.1.dist-info/top_level.txt
rxngraphormer-1.0.1.dist-info/RECORD
