Metadata-Version: 2.1
Name: rxngraphormer
Version: 1.0.1
Summary: Package for a novel graph-based transformer model for reaction prediction
Home-page: https://github.com/licheng-xu-echo/RXNGraphormer
Author: Li-Cheng Xu
Author-email: xulicheng@sais.com.cn
License: MIT License
License-File: LICENSE
Requires-Dist: Cython (==0.29.23)
Requires-Dist: h5py (==2.10.0)
Requires-Dist: html5lib (==1.1)
Requires-Dist: ipykernel (==5.3.4)
Requires-Dist: ipython (==7.22.0)
Requires-Dist: ipython-genutils (==0.2.0)
Requires-Dist: ipywidgets (==7.6.3)
Requires-Dist: isort (==5.8.0)
Requires-Dist: jdcal (==1.4.1)
Requires-Dist: jedi (==0.17.2)
Requires-Dist: jeepney (==0.6.0)
Requires-Dist: Jinja2 (==2.11.3)
Requires-Dist: joblib (==1.4.2)
Requires-Dist: json5 (==0.9.5)
Requires-Dist: jsonschema (==3.2.0)
Requires-Dist: jupyter (==1.0.0)
Requires-Dist: jupyter-client (==6.1.12)
Requires-Dist: jupyter-console (==6.4.0)
Requires-Dist: jupyter-core (==4.7.1)
Requires-Dist: jupyter-packaging (==0.7.12)
Requires-Dist: jupyter-server (==1.4.1)
Requires-Dist: lxml (==4.6.3)
Requires-Dist: matplotlib (==3.3.4)
Requires-Dist: networkx (==2.5)
Requires-Dist: numba (==0.53.1)
Requires-Dist: numexpr (==2.7.3)
Requires-Dist: numpy (==1.23.5)
Requires-Dist: numpydoc (==1.1.0)
Requires-Dist: OpenNMT-py (==1.2.0)
Requires-Dist: openpyxl (==3.0.7)
Requires-Dist: pandas (==1.2.4)
Requires-Dist: Pillow (==8.2.0)
Requires-Dist: pip (==24.2)
Requires-Dist: pyg-lib (==0.4.0+pt112cu113)
Requires-Dist: rdkit (==2024.3.2)
Requires-Dist: regex (==2021.4.4)
Requires-Dist: requests (==2.25.1)
Requires-Dist: scikit-image (==0.18.1)
Requires-Dist: scikit-learn (==1.3.2)
Requires-Dist: scipy (==1.10.1)
Requires-Dist: seaborn (==0.11.1)
Requires-Dist: setuptools (==69.0.0)
Requires-Dist: six (==1.15.0)
Requires-Dist: tensorboard (==2.14.0)
Requires-Dist: torch (==1.12.1+cu113)
Requires-Dist: torch-cluster (==1.6.0+pt112cu113)
Requires-Dist: torch-geometric (==2.3.1)
Requires-Dist: torch-scatter (==2.1.0+pt112cu113)
Requires-Dist: torch-sparse (==0.6.16+pt112cu113)
Requires-Dist: torch-spline-conv (==1.2.1+pt112cu113)
Requires-Dist: torchsummary (==1.5.1)
Requires-Dist: torchtext (==0.4.0)
Requires-Dist: tqdm (==4.59.0)
Requires-Dist: wheel (==0.36.2)
Requires-Dist: xlrd (==2.0.1)
Requires-Dist: XlsxWriter (==1.3.8)
Requires-Dist: xlwt (==1.3.0)
Requires-Dist: xmltodict (==0.12.0)
Requires-Dist: yapf (==0.31.0)
Requires-Dist: zc.lockfile (==3.0.post1)
Requires-Dist: zict (==2.0.0)
Requires-Dist: zipp (==3.4.1)
Requires-Dist: dgl (==0.5.2)
Requires-Dist: dgllife (==0.2.6)
Requires-Dist: rxnmapper (==0.4.0)
Requires-Dist: localmapper (==0.1.4)
Requires-Dist: python-box (==7.2.0)
Requires-Dist: jinja2 (==2.11.3)
Requires-Dist: MarkupSafe (==1.1.1)
